bivariate_choropleth/__init__.py
bivariate_choropleth/_modidx.py
bivariate_choropleth/core.py
bivariate_choropleth/example.py
bivariate_choropleth/grid_palette.py
bivariate_choropleth/plotting.py
bivariate_choropleth/shapefiles.py
bivariate_choropleth-0.0.1.dist-info/LICENSE
bivariate_choropleth-0.0.1.dist-info/METADATA
bivariate_choropleth-0.0.1.dist-info/WHEEL
bivariate_choropleth-0.0.1.dist-info/entry_points.txt
bivariate_choropleth-0.0.1.dist-info/top_level.txt
bivariate_choropleth-0.0.1.dist-info/RECORD
