Metadata-Version: 2.1
Name: bivariate-choropleth
Version: 0.0.1
Summary: Bivariate Choropleth plotting library
Home-page: https://github.com/Parkes2/bivariate_choropleth
Author: Joseph Parkes
Author-email: joseph.mj.parkes@hotmail.com
License: Apache Software License 2.0
Keywords: nbdev jupyter notebook python
Classifier: Development Status :: 4 - Beta
Classifier: Intended Audience :: Developers
Classifier: Natural Language :: English
Classifier: Programming Language :: Python :: 3.7
Classifier: Programming Language :: Python :: 3.8
Classifier: Programming Language :: Python :: 3.9
Classifier: Programming Language :: Python :: 3.10
Classifier: Programming Language :: Python :: 3.11
Classifier: Programming Language :: Python :: 3.12
Classifier: License :: OSI Approved :: Apache Software License
Requires-Python: >=3.7
License-File: LICENSE
Requires-Dist: fastcore
Requires-Dist: panda
Requires-Dist: geopandas
Requires-Dist: matplotlib
Requires-Dist: shapely
Requires-Dist: geodatasets
Provides-Extra: dev
